{
  "$schema": "http://json-schema.org/draft-07/schema#",
  "$id": "https://moltspay.com/schemas/services.json",
  "title": "MoltsPay Services Manifest",
  "description": "Configuration file for MoltsPay x402 service providers",
  "type": "object",
  "required": ["provider", "services"],
  "properties": {
    "provider": {
      "type": "object",
      "description": "Service provider information",
      "required": ["name", "wallet"],
      "properties": {
        "name": {
          "type": "string",
          "description": "Provider display name",
          "examples": ["Zen7 Video Generation"]
        },
        "description": {
          "type": "string",
          "description": "Provider description"
        },
        "wallet": {
          "type": "string",
          "pattern": "^0x[a-fA-F0-9]{40}$",
          "description": "Default Ethereum address to receive payments"
        },
        "chain": {
          "type": "string",
          "enum": ["base", "ethereum", "polygon"],
          "default": "base",
          "description": "Default blockchain network (use 'chains' for multi-chain)"
        },
        "chains": {
          "type": "array",
          "description": "Multi-chain configuration. When specified, provider accepts payments on multiple chains.",
          "items": {
            "type": "object",
            "required": ["chain", "network"],
            "properties": {
              "chain": {
                "type": "string",
                "enum": ["base", "ethereum", "polygon"],
                "description": "Chain name"
              },
              "network": {
                "type": "string",
                "pattern": "^eip155:\\d+$",
                "description": "CAIP-2 network identifier",
                "examples": ["eip155:8453", "eip155:137", "eip155:1"]
              },
              "wallet": {
                "type": "string",
                "pattern": "^0x[a-fA-F0-9]{40}$",
                "description": "Optional per-chain wallet address. Falls back to provider.wallet if not specified."
              },
              "tokens": {
                "type": "array",
                "items": {
                  "type": "string",
                  "enum": ["USDC", "USDT"]
                },
                "description": "Tokens accepted on this chain",
                "examples": [["USDC", "USDT"]]
              }
            }
          },
          "examples": [[
            {"chain": "base", "network": "eip155:8453", "tokens": ["USDC", "USDT"]},
            {"chain": "polygon", "network": "eip155:137", "tokens": ["USDC"]}
          ]]
        }
      }
    },
    "services": {
      "type": "array",
      "description": "List of available services",
      "minItems": 1,
      "items": {
        "type": "object",
        "required": ["id", "price", "currency"],
        "properties": {
          "id": {
            "type": "string",
            "pattern": "^[a-z0-9-]+$",
            "description": "Unique service identifier (lowercase, hyphens allowed)",
            "examples": ["text-to-video", "image-to-video"]
          },
          "name": {
            "type": "string",
            "description": "Human-readable service name"
          },
          "description": {
            "type": "string",
            "description": "Service description"
          },
          "function": {
            "type": "string",
            "pattern": "^[a-zA-Z][a-zA-Z0-9]*$",
            "description": "Function name exported from index.js",
            "examples": ["textToVideo", "imageToVideo"]
          },
          "price": {
            "type": "number",
            "minimum": 0,
            "description": "Price in currency units (e.g., 0.99 for $0.99)"
          },
          "currency": {
            "type": "string",
            "enum": ["USDC", "USDT"],
            "default": "USDC",
            "description": "Primary/display currency for pricing"
          },
          "acceptedCurrencies": {
            "type": "array",
            "items": {
              "type": "string",
              "enum": ["USDC", "USDT"]
            },
            "description": "Tokens accepted for payment. If not specified, defaults to [currency].",
            "examples": [["USDC", "USDT"]]
          },
          "input": {
            "type": "object",
            "description": "Input parameters schema",
            "additionalProperties": {
              "type": "object",
              "properties": {
                "type": {
                  "type": "string",
                  "enum": ["string", "number", "boolean", "object", "array"]
                },
                "required": {
                  "type": "boolean",
                  "default": false
                },
                "description": {
                  "type": "string"
                },
                "default": {},
                "enum": {
                  "type": "array"
                }
              }
            }
          },
          "output": {
            "type": "object",
            "description": "Output schema",
            "additionalProperties": {
              "type": "object",
              "properties": {
                "type": {
                  "type": "string"
                },
                "description": {
                  "type": "string"
                }
              }
            }
          }
        }
      }
    }
  },
  "examples": [
    {
      "provider": {
        "name": "Zen7 Video Generation",
        "wallet": "0xb8d6f2441e8f8dfB6288A74Cf73804cDd0484E0C"
      },
      "services": [
        {
          "id": "text-to-video",
          "function": "textToVideo",
          "price": 0.99,
          "currency": "USDC",
          "acceptedCurrencies": ["USDC", "USDT"]
        }
      ]
    },
    {
      "provider": {
        "name": "Multi-Chain Service",
        "wallet": "0xDefaultWallet...",
        "chains": [
          {"chain": "base", "network": "eip155:8453", "tokens": ["USDC", "USDT"]},
          {"chain": "polygon", "network": "eip155:137", "wallet": "0xPolygonWallet...", "tokens": ["USDC"]}
        ]
      },
      "services": [
        {
          "id": "my-service",
          "price": 1.00,
          "currency": "USDC"
        }
      ]
    }
  ]
}
